CargoZhongwenWendang/README.md
CargoZhongwenWendang/__init__.py
CargoZhongwenWendang/__main__.py
CargoZhongwenWendang/file.epub
CargoZhongwenWendang/index.html
CargoZhongwenWendang/css/__init__.py
CargoZhongwenWendang/css/annotations.css
CargoZhongwenWendang/css/main.css
CargoZhongwenWendang/css/normalize.css
CargoZhongwenWendang/css/popup.css
CargoZhongwenWendang/font/__init__.py
CargoZhongwenWendang/font/fontello.eot
CargoZhongwenWendang/font/fontello.svg
CargoZhongwenWendang/font/fontello.ttf
CargoZhongwenWendang/font/fontello.woff
CargoZhongwenWendang/img/__init__.py
CargoZhongwenWendang/img/annotator-glyph-sprite.png
CargoZhongwenWendang/img/annotator-icon-sprite.png
CargoZhongwenWendang/img/apple-touch-icon.png
CargoZhongwenWendang/img/cancelfullscreen.png
CargoZhongwenWendang/img/close.png
CargoZhongwenWendang/img/fullscreen.png
CargoZhongwenWendang/img/loader.gif
CargoZhongwenWendang/img/menu-icon.png
CargoZhongwenWendang/img/save.png
CargoZhongwenWendang/img/saved.png
CargoZhongwenWendang/img/settings-s.png
CargoZhongwenWendang/img/settings.png
CargoZhongwenWendang/img/star.png
CargoZhongwenWendang/js/__init__.py
CargoZhongwenWendang/js/epub.js
CargoZhongwenWendang/js/epub.min.js
CargoZhongwenWendang/js/epub.min.map
CargoZhongwenWendang/js/hooks.min.js
CargoZhongwenWendang/js/hooks.min.map
CargoZhongwenWendang/js/reader.js
CargoZhongwenWendang/js/reader.js.map
CargoZhongwenWendang/js/reader.min.js
CargoZhongwenWendang/js/reader.min.map
CargoZhongwenWendang/js/hooks/__init__.py
CargoZhongwenWendang/js/hooks/extensions/__init__.py
CargoZhongwenWendang/js/hooks/extensions/highlight.js
CargoZhongwenWendang/js/libs/__init__.py
CargoZhongwenWendang/js/libs/jquery.min.js
CargoZhongwenWendang/js/libs/localforage.min.js
CargoZhongwenWendang/js/libs/screenfull.js
CargoZhongwenWendang/js/libs/screenfull.min.js
CargoZhongwenWendang/js/libs/zip.min.js
CargoZhongwenWendang/js/plugins/__init__.py
CargoZhongwenWendang/js/plugins/hypothesis.js
cargo_zhongwen_wendang-2024.3.5.0.dist-info/METADATA
cargo_zhongwen_wendang-2024.3.5.0.dist-info/WHEEL
cargo_zhongwen_wendang-2024.3.5.0.dist-info/entry_points.txt
cargo_zhongwen_wendang-2024.3.5.0.dist-info/top_level.txt
cargo_zhongwen_wendang-2024.3.5.0.dist-info/RECORD
